batch_pdf/__init__.py
batch_pdf/pdfbase/__init__.py
batch_pdf/pdfbase/batch_list.py
batch_pdf/pdfbase/pdf_doc.py
batch_pdf/pdfgen/__init__.py
batch_pdf/pdfgen/pdf_generator.py
test/__init__.py
test/origin.py
test/pdf_wrapper.py
batch_pdf-0.1.1.dist-info/METADATA
batch_pdf-0.1.1.dist-info/WHEEL
batch_pdf-0.1.1.dist-info/top_level.txt
batch_pdf-0.1.1.dist-info/RECORD
